LICENSE
MANIFEST.in
README.md
setup.py
text2vec/__init__.py
text2vec/bertmatching_dataset.py
text2vec/bertmatching_model.py
text2vec/bge_dataset.py
text2vec/bge_model.py
text2vec/bm25.py
text2vec/cli.py
text2vec/cosent_dataset.py
text2vec/cosent_model.py
text2vec/ngram.py
text2vec/sentence_model.py
text2vec/sentencebert_model.py
text2vec/similarity.py
text2vec/stopwords.txt
text2vec/text_matching_dataset.py
text2vec/version.py
text2vec/word2vec.py
text2vec.egg-info/PKG-INFO
text2vec.egg-info/SOURCES.txt
text2vec.egg-info/dependency_links.txt
text2vec.egg-info/entry_points.txt
text2vec.egg-info/not-zip-safe
text2vec.egg-info/requires.txt
text2vec.egg-info/top_level.txt
text2vec/utils/__init__.py
text2vec/utils/distance.py
text2vec/utils/get_file.py
text2vec/utils/io_util.py
text2vec/utils/rank_bm25.py
text2vec/utils/stats_util.py
text2vec/utils/tokenizer.py