Metadata-Version: 2.4
Name: text2vec
Version: 1.3.7
Summary: Text to vector Tool, encode text
Home-page: https://github.com/shibing624/text2vec
Author: XuMing
Author-email: xuming624@qq.com
License: Apache License 2.0
Keywords: word embedding,text2vec,Chinese Text Similarity Calculation Tool,similarity,word2vec
Classifier: Development Status :: 5 - Production/Stable
Classifier: Intended Audience :: Developers
Classifier: Intended Audience :: Education
Classifier: Intended Audience :: Science/Research
Classifier: License :: OSI Approved :: Apache Software License
Classifier: Operating System :: OS Independent
Classifier: Programming Language :: Python :: 3
Classifier: Topic :: Scientific/Engineering :: Artificial Intelligence
Requires-Python: >=3.6.0
License-File: LICENSE
Requires-Dist: jieba
Requires-Dist: loguru
Requires-Dist: transformers
Requires-Dist: datasets
Requires-Dist: tqdm
Requires-Dist: scikit-learn
Requires-Dist: pandas
Dynamic: author
Dynamic: author-email
Dynamic: classifier
Dynamic: description
Dynamic: description-content-type
Dynamic: home-page
Dynamic: keywords
Dynamic: license
Dynamic: license-file
Dynamic: requires-dist
Dynamic: requires-python
Dynamic: summary
